Workbook
Name aporte: MGK_INVEST_APP!$D$20
Name patrimonio_acumulado: MGK_INVEST_APP!$D$23
Name qtde_anos: MGK_INVEST_APP!$D$21
Name rendimento_carteira: MGK_INVEST_APP!$D$15
Name salario: MGK_INVEST_APP!$D$14
Name sugestao_investimento: MGK_INVEST_APP!$D$16
Name tx_rendimento_mensal: MGK_INVEST_APP!$D$22

Sheet MGK_INVEST_APP
B13: CONFIGURAÇÕES
B14: Salário | D14: 5000
B15: Rendimento Carteira | D15: 0.006
B16: Sugestão de Investimento (30%) | D16: =D14*30% -> 1500
B19: INVESTIMENTO MENSAL
B20: Quanto Investir por Mês? | D20: 1500
B21: Por Quantos Anos? | D21: 10
B22: Taxa de Rendimento Mensal? | D22: 0.01079
B23: Patrimônio acumulado? | D23: =FV(D22,D21*12,D20*-1) -> 364926.32
B24: Dividendos Mensais? | D24: =patrimonio_acumulado*tx_rendimento_mensal -> 3937.555
B27: Cenários | D27: Dividendos
A28: 2 | B28: Quanto em 2 Anos? | C28: =FV(tx_rendimento_mensal,$A28*12,aporte*-1) -> 40841.441 | D28: =$C28*tx_rendimento_mensal -> 440.67915
A29: 5 | B29: Quanto em 5 Anos? | C29: =FV(tx_rendimento_mensal,$A29*12,aporte*-1) -> 125665.37 | D29: =$C29*tx_rendimento_mensal -> 1355.9294
A30: 10 | B30: Quanto em 10 Anos? | C30: =FV(tx_rendimento_mensal,$A30*12,aporte*-1) -> 364926.32 | D30: =$C30*tx_rendimento_mensal -> 3937.555
A31: 20 | B31: Quanto em 20 Anos? | C31: =FV(tx_rendimento_mensal,$A31*12,aporte*-1) -> 1687797.6 | D31: =$C31*tx_rendimento_mensal -> 18211.336
A32: 30 | B32: Quanto em 30 Anos? | C32: =FV(tx_rendimento_mensal,$A32*12,aporte*-1) -> 6483254.5 | D32: =$C32*tx_rendimento_mensal -> 69954.316
B35: Perfil | C35: Conservador
B36: VALOR A SER INVESTIDO POR MÊS | C36: =aporte -> 1500
B38: Tipo de FII | C38: Percentual Sugerido | D38: Valores
B39: PAPEL | C39: =VLOOKUP($C$35&"-"&B39,apoio!B5:E22,4,FALSE) -> 0.3 | D39: =$C$36*C39 -> 450
B40: TIJOLO | C40: =VLOOKUP($C$35&"-"&B40,apoio!B6:E23,4,FALSE) -> 0.5 | D40: =$C$36*C40 -> 750
B41: HÍBRIDOS | C41: =VLOOKUP($C$35&"-"&B41,apoio!B7:E24,4,FALSE) -> 0.1 | D41: =$C$36*C41 -> 150
B42: FOFs | C42: =VLOOKUP($C$35&"-"&B42,apoio!B8:E25,4,FALSE) -> 0.1 | D42: =$C$36*C42 -> 150
B43: DESENVOLVIMENTO | C43: =VLOOKUP($C$35&"-"&B43,apoio!B9:E26,4,FALSE) -> 0 | D43: =$C$36*C43 -> 0
B44: HOTELARIAS | C44: =VLOOKUP($C$35&"-"&B44,apoio!B10:E27,4,FALSE) -> 0 | D44: =$C$36*C44 -> 0
D45: =SUM(D39:D44) -> 1500

Sheet apoio
C4: Perfil | D4: Tipo de FII | E4: Percentual Sugerido
B5: =C5&"-"&D5 -> Conservador-PAPEL | C5: Conservador | D5: PAPEL | E5: 0.3
B6: =C6&"-"&D6 -> Conservador-TIJOLO | C6: Conservador | D6: TIJOLO | E6: 0.5
B7: =C7&"-"&D7 -> Conservador-HÍBRIDOS | C7: Conservador | D7: HÍBRIDOS | E7: 0.1
B8: =C8&"-"&D8 -> Conservador-FOFs | C8: Conservador | D8: FOFs | E8: 0.1
B9: =C9&"-"&D9 -> Conservador-DESENVOLVIMENTO | C9: Conservador | D9: DESENVOLVIMENTO | E9: 0
B10: =C10&"-"&D10 -> Conservador-HOTELARIAS | C10: Conservador | D10: HOTELARIAS | E10: 0
B11: =C11&"-"&D11 -> Moderado-PAPEL | C11: Moderado | D11: PAPEL | E11: 0.32
B12: =C12&"-"&D12 -> Moderado-TIJOLO | C12: Moderado | D12: TIJOLO | E12: 0.35
B13: =C13&"-"&D13 -> Moderado-HÍBRIDOS | C13: Moderado | D13: HÍBRIDOS | E13: 0.08
B14: =C14&"-"&D14 -> Moderado-FOFs | C14: Moderado | D14: FOFs | E14: 0.05
B15: =C15&"-"&D15 -> Moderado-DESENVOLVIMENTO | C15: Moderado | D15: DESENVOLVIMENTO | E15: 0.1
B16: =C16&"-"&D16 -> Moderado-HOTELARIAS | C16: Moderado | D16: HOTELARIAS | E16: 0.1
... B22: =C22&"-"&D22 -> Agressivo-HOTELARIAS | C22: Agressivo | D22: HOTELARIAS | E22: 0.1
